odoo/addons/l10n_cl_chart_of_account/README.rst
odoo/addons/l10n_cl_chart_of_account/__init__.py
odoo/addons/l10n_cl_chart_of_account/__manifest__.py
odoo/addons/l10n_cl_chart_of_account/data/account_chart_template_data.xml
odoo/addons/l10n_cl_chart_of_account/data/account_journal.xml
odoo/addons/l10n_cl_chart_of_account/data/account_tax_data.xml
odoo/addons/l10n_cl_chart_of_account/data/l10n_cl_chart_of_account_data.xml
odoo/addons/l10n_cl_chart_of_account/i18n/es_CL.po
odoo/addons/l10n_cl_chart_of_account/i18n/l10n_cl_chart_of_account.pot
odoo/addons/l10n_cl_chart_of_account/models/__init__.py
odoo/addons/l10n_cl_chart_of_account/models/account_invoice.py
odoo/addons/l10n_cl_chart_of_account/models/account_invoice_tax.py
odoo/addons/l10n_cl_chart_of_account/models/account_tax.py
odoo/addons/l10n_cl_chart_of_account/readme/CONTRIBUTORS.rst
odoo/addons/l10n_cl_chart_of_account/readme/DESCRIPTION.rst
odoo/addons/l10n_cl_chart_of_account/readme/USAGE.rst
odoo/addons/l10n_cl_chart_of_account/static/description/icon.png
odoo/addons/l10n_cl_chart_of_account/static/description/index.html
odoo/addons/l10n_cl_chart_of_account/views/account_tax.xml
odoo/addons/l10n_cl_chart_of_account/views/menu.xml
odoo12_addon_l10n_cl_chart_of_account-12.0.1.0.1.dist-info/METADATA
odoo12_addon_l10n_cl_chart_of_account-12.0.1.0.1.dist-info/WHEEL
odoo12_addon_l10n_cl_chart_of_account-12.0.1.0.1.dist-info/top_level.txt
odoo12_addon_l10n_cl_chart_of_account-12.0.1.0.1.dist-info/RECORD
